{
    "seed" : 2017,
    "save_path" : "/home/dzubke/awni_speech/speech/examples/librispeech/models/ctc_models/20200128/v2",

    "data" : {
        "train_set" : "/home/dzubke/awni_speech/data/dustin_test_data/20191202_clean/drz_test.json",
        "dev_set" : "/home/dzubke/awni_speech/data/dustin_test_data/20191202_clean/drz_test.json",
        "start_and_end" : false
    },

    "optimizer" : {
        "batch_size" : 1,
        "epochs" : 100,
        "learning_rate" : 1e-3,
        "momentum" : 0.0
    },

    "model" : {
        "class" : "CTC",
        "dropout" : 0.0,
        "encoder" : {
            "conv" : [
                [32, 5, 32, 1]
             ],
            "rnn" : {
                "dim" : 256,
                "bidirectional" : false,
                "layers" : 1
            }
        }
    }
}
