{"prediction": ["sil", "hh", "iy", "s", "er", "v", "iy", "ih", "z", "ax", "p", "ah", "n", "cl", "k", "uw", "m", "n", "iy", "n", "ih", "vcl", "f", "er", "ax", "th", "hh", "ih", "vcl", "k", "l", "ah", "n", "ch", "sil"], "label": ["sil", "p", "iy", "cl", "s", "er", "r", "iy", "ix", "z", "aa", "r", "cl", "k", "ix", "n", "v", "iy", "n", "y", "ix", "n", "cl", "f", "er", "ix", "cl", "k", "w", "ih", "cl", "k", "l", "ah", "n", "cl", "ch", "sil"]}
{"prediction": ["sil", "hh", "ih", "z", "cl", "p", "ae", "m", "ih", "n", "m", "w", "ah", "z", "th", "iy", "n", "hh", "ae", "vcl", "g", "er", "n", "vcl", "d", "sil", "hh", "ih", "n", "hh", "ih", "z", "vcl", "b", "y", "uw", "n", "hh", "el", "vcl", "b", "uw", "vcl", "z", "hh", "er", "m", "y", "aa", "n", "ih", "n", "sh", "hh", "ae", "n", "vcl", "b", "iy", "sil"], "label": ["sil", "hh", "ih", "z", "cl", "k", "ae", "cl", "t", "ix", "n", "w", "ax", "s", "th", "ih", "n", "ae", "n", "hh", "ae", "vcl", "g", "er", "vcl", "d", "ix", "n", "ih", "z", "vcl", "b", "y", "uw", "dx", "uw", "f", "el", "vcl", "b", "uw", "cl", "t", "s", "epi", "w", "er", "w", "ao", "r", "n", "ix", "n", "epi", "sh", "ae", "vcl", "b", "iy", "sil"]}
{"prediction": ["sil", "hh", "eh", "m", "n", "iy", "z", "ih", "n", "z", "f", "ah", "dh", "ih", "s", "cl", "t", "ay", "v", "z", "iy", "n", "hh", "uw", "l", "ix", "sh", "n", "ae", "sil"], "label": ["sil", "dh", "ix", "r", "iy", "z", "ax", "n", "z", "f", "er", "dh", "ih", "s", "vcl", "d", "ay", "v", "s", "iy", "m", "vcl", "d", "f", "uw", "l", "ix", "sh", "epi", "n", "aw", "sil"]}
{"prediction": ["sil", "hh", "aw", "n", "d", "er", "l", "iy", "cl", "p", "iy", "vcl", "b", "l", "ax", "hh", "aa", "r", "aa", "s", "cl", "t", "ix", "n", "ix", "s", "hh", "l", "uw", "vcl", "d", "ix", "n", "sil"], "label": ["sil", "eh", "l", "vcl", "d", "er", "l", "iy", "cl", "p", "iy", "cl", "p", "el", "er", "aa", "f", "ix", "n", "ix", "cl", "k", "s", "cl", "k", "l", "uw", "vcl", "d", "ix", "vcl", "d", "sil"]}
{"prediction": ["sil", "hh", "r", "uw", "n", "eh", "m", "sh", "ix", "m", "m", "iy", "f", "ao", "sil", "hh", "ay", "er", "m", "ax", "l", "ow", "eh", "s", "cl", "p", "ix", "n", "cl", "t", "iy", "sh", "en", "sil"], "label": ["sil", "p", "er", "vcl", "d", "ah", "cl", "k", "sh", "ix", "n", "m", "ey", "f", "ao", "l", "f", "aa", "r", "vcl", "b", "ax", "l", "ow", "ax", "cl", "k", "s", "cl", "p", "ix", "cl", "t", "ey", "sh", "en", "cl", "s", "sil"]}
