{"prediction": ["aa", "d", "ah", "m", "m", "ey", "n", "d", "hh", "ow"], "label": ["t", "ah", "m", "ey", "t", "ow"]}
{"prediction": ["er", "aw", "eh", "n", "er", "d", "iy", "y", "uw", "l", "ih", "ng", "g", "ah", "v", "dh", "iy", "w", "eh", "l", "dh", "er", "z", "ih", "n", "dh", "aw"], "label": ["w", "ah", "t", "d", "uw", "y", "uw", "th", "ih", "ng", "k", "ah", "v", "dh", "ah", "w", "eh", "dh", "er", "t", "ah", "d", "ey"]}
{"prediction": ["ay", "dh", "ow", "r", "ey", "n", "ae", "n", "z", "p", "ey", "aa", "v", "ao", "l", "z", "m", "ey", "n", "l", "ey", "r", "dh", "iy", "hh", "eh", "n", "l", "er"], "label": ["dh", "ah", "r", "ey", "n", "ih", "n", "s", "p", "ey", "n", "f", "ao", "l", "z", "m", "ey", "n", "l", "iy", "aa", "n", "dh", "ah", "p", "l", "ey", "n"]}
{"prediction": ["m", "er", "r", "d", "ah", "l", "uw", "ih", "ng", "eh", "t", "w", "iy", "b", "r", "aw", "n", "ah", "th", "aa", "r", "ah", "s", "er", "sh", "ah", "m", "r", "d", "ah", "v", "l", "ow", "v", "er", "dh", "iy", "l", "ey", "z", "iy", "d", "aa", "l", "er"], "label": ["dh", "ah", "k", "w", "ih", "k", "b", "r", "aw", "n", "f", "aa", "k", "s", "jh", "ah", "m", "p", "t", "ow", "v", "er", "dh", "ah", "l", "ey", "z", "iy", "d", "ao", "g"]}
{"prediction": ["ay", "ay", "eh", "m", "ay", "r", "ih", "z", "ih", "v", "ih", "d", "ah", "n", "w", "aw", "ah", "v", "ae", "m", "ay", "hh", "aa", "d", "ah", "n", "r", "ih", "s", "d", "ey", "w", "ih", "th", "ey", "v", "eh", "r", "iy", "k", "ay", "n", "d", "ih", "k", "ah", "m", "v", "ah"], "label": ["w", "eh", "n", "ay", "v", "ih", "z", "ih", "t", "ih", "d", "ah", "l", "ae", "b", "ah", "m", "ah", "ay", "s", "t", "ey", "d", "w", "ih", "dh", "ey", "v", "eh", "r", "iy", "k", "ay", "n", "d", "k", "ah", "p", "ah", "l"]}
{"prediction": ["ay", "hh", "ow", "l", "ow"], "label": ["hh", "ah", "l", "ow"]}
{"prediction": ["r", "aa", "t", "hh", "ae", "v", "d", "ey", "n", "iy", "ih", "z", "er", "w", "ih", "n", "s", "t", "aw", "r", "er"], "label": ["t", "ah", "d", "ey", "ih", "z", "w", "eh", "n", "z", "d", "ey"]}
{"prediction": ["aa", "hh", "uh", "d", "l", "ay"], "label": ["g", "uh", "d", "b", "ay"]}
{"prediction": ["hh", "ay", "ay", "dh", "ow", "r", "ah", "n", "r", "d", "ao", "r", "ah", "v", "dh", "iy", "v", "aa", "r", "n", "eh", "z", "ow", "v", "er", "ah", "n", "r"], "label": ["dh", "ah", "f", "r", "ah", "n", "t", "d", "ao", "r", "ah", "v", "dh", "ah", "b", "aa", "r", "n", "ih", "z", "ow", "p", "ah", "n"]}
