{"prediction": ["n", "ay", "dh", "ow", "r", "ey", "n", "n", "z", "p", "ey", "n", "f", "ao", "l", "z", "m", "iy", "n", "l", "ey", "n", "ao", "n", "dh", "iy", "v", "hh", "ae", "v", "l", "ey"], "label": ["dh", "ah", "r", "ey", "n", "ih", "n", "s", "p", "ey", "n", "f", "ao", "l", "z", "m", "ey", "n", "l", "iy", "aa", "n", "dh", "ah", "p", "l", "ey", "n"]}
{"prediction": ["ay", "ah", "n", "ay", "v", "ih", "z", "ih", "t", "ih", "n", "ae", "ah", "n", "m", "ae", "m", "ao", "n", "ah", "r", "ey", "s", "t", "ey", "n", "w", "ih", "th", "ey", "v", "eh", "r", "iy", "k", "ay", "n", "d", "k", "ah", "m", "v", "ah", "l"], "label": ["w", "eh", "n", "ay", "v", "ih", "z", "ih", "t", "ih", "d", "ah", "l", "ae", "b", "ah", "m", "ah", "ay", "s", "t", "ey", "d", "w", "ih", "dh", "ey", "v", "eh", "r", "iy", "k", "ay", "n", "d", "k", "ah", "p", "ah", "l"]}
{"prediction": ["ay", "ao", "t", "f", "r", "ah", "n", "t", "ao", "r", "ah", "n", "dh", "ah", "v", "b", "aa", "n", "ih", "z", "hh", "ow", "t", "ah", "n"], "label": ["dh", "ah", "f", "r", "ah", "n", "t", "d", "ao", "r", "ah", "v", "dh", "ah", "b", "aa", "r", "n", "ih", "z", "ow", "p", "ah", "n"]}
{"prediction": ["aa", "ah", "m", "m", "ey", "t", "ow"], "label": ["t", "ah", "m", "ey", "t", "ow"]}
{"prediction": ["uh", "d", "ay"], "label": ["g", "uh", "d", "b", "ay"]}
{"prediction": ["l", "ow"], "label": ["hh", "ah", "l", "ow"]}
{"prediction": ["v", "k", "w", "ih", "ng", "k", "ah", "m", "r", "aw", "n", "th", "ao", "ng", "z", "sh", "ae", "m", "t", "ah", "v", "dh", "ow", "v", "er", "dh", "ow", "l", "iy", "z", "iy", "d", "ao", "g"], "label": ["dh", "ah", "k", "w", "ih", "k", "b", "r", "aw", "n", "f", "aa", "k", "s", "jh", "ah", "m", "p", "t", "ow", "v", "er", "dh", "ah", "l", "ey", "z", "iy", "d", "ao", "g"]}
{"prediction": ["ay", "w", "ih", "n", "ao", "n", "y", "l", "ih", "ng", "k", "ah", "v", "dh", "iy", "w", "eh", "dh", "er", "n", "z", "uw", "m", "ey"], "label": ["w", "ah", "t", "d", "uw", "y", "uw", "th", "ih", "ng", "k", "ah", "v", "dh", "ah", "w", "eh", "dh", "er", "t", "ah", "d", "ey"]}
{"prediction": ["ay", "z", "ae", "v", "n", "ey", "ih", "z", "w", "ih", "n", "s", "t", "ey"], "label": ["t", "ah", "d", "ey", "ih", "z", "w", "eh", "n", "z", "d", "ey"]}
